Metadata-Version: 2.4
Name: think-ai-consciousness
Version: 2.2.0
Summary: Distributed AGI Architecture with exponential intelligence growth, O(1) complexity, and autonomous evolution - Now with Google Colab support!
Home-page: https://github.com/champi-dev/think_ai
Author: Champi (BDFL)
Author-email: danielsarcor@gmail.com
Project-URL: Bug Reports, https://github.com/champi-dev/think_ai/issues
Project-URL: Source, https://github.com/champi-dev/think_ai
Project-URL: Documentation, https://github.com/champi-dev/think_ai/blob/main/README.md
Keywords: agi artificial-general-intelligence distributed-systems exponential-growth consciousness philosophy self-training knowledge-creation o1-complexity bdfl
Classifier: Development Status :: 4 - Beta
Classifier: Intended Audience :: Developers
Classifier: Topic :: Scientific/Engineering :: Artificial Intelligence
Classifier: License :: OSI Approved :: MIT License
Classifier: Programming Language :: Python :: 3
Classifier: Programming Language :: Python :: 3.8
Classifier: Programming Language :: Python :: 3.9
Classifier: Programming Language :: Python :: 3.10
Classifier: Programming Language :: Python :: 3.11
Classifier: Programming Language :: Python :: 3.12
Classifier: Operating System :: OS Independent
Classifier: Environment :: GPU :: NVIDIA CUDA
Classifier: Environment :: Console
Requires-Python: >=3.8
Requires-Dist: asyncio-throttle==1.0.2
Requires-Dist: structlog==24.1.0
Requires-Dist: rich==13.7.1
Requires-Dist: python-dotenv==1.0.1
Requires-Dist: cassandra-driver==3.29.0
Requires-Dist: redis==5.0.1
Requires-Dist: neo4j==5.16.0
Requires-Dist: torch>=2.1.0
Requires-Dist: transformers>=4.36.0
Requires-Dist: sentence-transformers==2.2.2
Requires-Dist: numpy>=1.26.0
Requires-Dist: scikit-learn==1.3.2
Requires-Dist: annoy>=1.17.0
Requires-Dist: onnxruntime>=1.17.0
Requires-Dist: onnx>=1.15.0
Requires-Dist: safetensors>=0.4.1
Requires-Dist: accelerate>=0.25.0
Requires-Dist: bitsandbytes>=0.41.3
Requires-Dist: optimum>=1.16.0
Requires-Dist: fastapi==0.108.0
Requires-Dist: uvicorn==0.25.0
Requires-Dist: aiofiles==23.2.1
Requires-Dist: httpx==0.25.2
Requires-Dist: aiofiles==23.2.1
Requires-Dist: psutil==5.9.6
Requires-Dist: pyyaml==6.0.1
Requires-Dist: click==8.1.7
Requires-Dist: prompt-toolkit==3.0.43
Provides-Extra: dev
Requires-Dist: pytest>=7.0; extra == "dev"
Requires-Dist: pytest-cov>=4.0.0; extra == "dev"
Requires-Dist: pytest-asyncio>=0.20; extra == "dev"
Requires-Dist: pre-commit>=3.0.0; extra == "dev"
Provides-Extra: full
Requires-Dist: playwright>=1.30; extra == "full"
Requires-Dist: pillow>=9.0; extra == "full"
Requires-Dist: numpy>=1.20; extra == "full"
Requires-Dist: pandas>=1.3; extra == "full"
Dynamic: author
Dynamic: author-email
Dynamic: classifier
Dynamic: description
Dynamic: description-content-type
Dynamic: home-page
Dynamic: keywords
Dynamic: project-url
Dynamic: provides-extra
Dynamic: requires-dist
Dynamic: requires-python
Dynamic: summary
